README.rst
setup.py
Py2SQL/__init__.py
Py2SQL/__main__.py
Py2SQL/config.py
Py2SQL/py2sql.py
Py2SQL/sql_queries.py
Py2SQL/util_for_db.py
Py2SQL/util_for_handle_usual_data.py
cmd_Py2SQL.egg-info/PKG-INFO
cmd_Py2SQL.egg-info/SOURCES.txt
cmd_Py2SQL.egg-info/dependency_links.txt
cmd_Py2SQL.egg-info/entry_points.txt
cmd_Py2SQL.egg-info/top_level.txt