Metadata-Version: 1.0
Name: cmd-Py2SQL
Version: 0.3.1
Summary: Python command line application bare bones template.
Home-page: UNKNOWN
Author: Makhanko_Mospan_Syzko
Author-email: UNKNOWN
License: UNKNOWN
Platform: UNKNOWN
